{
    "siteInfo": {
        "foundations": [
            {
                "id": "1",
                "name": "Fundacja1",
                "description": "Description",
                "needs": "item1, item2, item3, item4"

            },
            {
                "id": "2",
                "name": "Fundacja2",
                "description": "Description",
                "needs": "item1, item2, item3, item4"

            },
            {
                "id": "3",
                "name": "Fundacja3",
                "description": "Description",
                "needs": "item1, item2, item3, item4"
            },
            {
                "id": "4",
                "name": "Fundacja4",
                "description": "Description",
                "needs": "item1, item2, item3, item4"
            }
        ],
        "organizations": [
            {
                "id": "1",
                "name": "Organizacja1",
                "description": "Description",
                "needs": "item1, item2, item3, item4"
            },
            {
                "id": "2",
                "name": "Organizacja2",
                "description": "Description",
                "needs": "item1, item2, item3, item4"
            },
            {
                "id": "3",
                "name": "Organizacja3",
                "description": "Description",
                "needs": "item1, item2, item3, item4"
            },
            {
                "id": "4",
                "name": "Organizacja4",
                "description": "Description",
                "needs": "item1, item2, item3, item4"
            },
            {
                "id": "5",
                "name": "Organizacja5",
                "description": "Description",
                "needs": "item1, item2, item3, item4"
            },
            {
                "id": "6",
                "name": "Organizacja6",
                "description": "Description",
                "needs": "item1, item2, item3, item4"
            },
            {
                "id": "1",
                "name": "Organizacja7",
                "description": "Description",
                "needs": "item1, item2, item3, item4"
            }
        ],
        "local": [
            {
                "id": "1",
                "name": "Lokalna zbi贸rka1",
                "description": "Description",
                "needs": "item1, item2, item3, item4"
            },
            {
                "id": "2",
                "name": "Lokalna zbi贸rka12",
                "description": "Description",
                "needs": "item1, item2, item3, item4"
            },
            {
                "id": "3",
                "name": "Lokalna zbi贸rka13",
                "description": "Description",
                "needs": "item1, item2, item3, item4"
            },
            {
                "id": "4",
                "name": "Lokalna zbi贸rka14",
                "description": "Description",
                "needs": "item1, item2, item3, item4"
            }
        ]
    }
}
